{
  "url":
    "https://www.homedepot.com/p/Rugg-Manufacturing-20-in-Ergonomic-Aluminum-Poly-Combo-Blade-Snow-Shovel-36PBSLW1/203814970",
  "title": "20 in. Ergonomic Aluminum Poly Combo Blade Snow Shovel",
  "brand": "Rugg Manufacturing",
  "category": "snowShovel",
  "price": 4666,
  "description":
    "The Original Back-Saver snow shovel is the first ergonomic snow shovel marketed internationally. The design reduces the stress put on your back as you shovel. The material used are second to none assuring this tool will be used for a very long time.",
  "imageUrl":
    "https://images.homedepot-static.com/productImages/17a58e04-d576-4ff1-86ff-34f8cf8aae8a/svn/rugg-manufacturing-snow-shovels-ice-scrapers-36pbslw1-64_1000.jpg",
  "quantity": 0
}
